shivml/__init__.py
shivml/model_trainer.py
shivml/preprocessing.py
shivml/utils.py
shivml-0.0.1.dist-info/METADATA
shivml-0.0.1.dist-info/WHEEL
shivml-0.0.1.dist-info/top_level.txt
shivml-0.0.1.dist-info/RECORD
