Metadata-Version: 2.4
Name: shivml
Version: 0.0.1
Summary: An automatic Machine Learning trainer by Shivam.
Author: Shivam Vinod Chaudhari
Author-email: shivam7744998850@gmail.com
Requires-Python: >=3.6
Requires-Dist: pandas
Requires-Dist: scikit-learn
Requires-Dist: joblib
Dynamic: author
Dynamic: author-email
Dynamic: description
Dynamic: description-content-type
Dynamic: requires-dist
Dynamic: requires-python
Dynamic: summary
